xDNN/__init__.py
xDNN/featureExtraction.py
xDNN/myfunctions.py
xDNN/xDNN_class_softmax.py
xDNN_classifier/__init__.py
xDNN_classifier/featureExtraction.py
xDNN_classifier/myfunctions.py
xDNN_classifier/xDNN_class_softmax.py
xDNN_classifier-0.1.21.dist-info/METADATA
xDNN_classifier-0.1.21.dist-info/WHEEL
xDNN_classifier-0.1.21.dist-info/top_level.txt
xDNN_classifier-0.1.21.dist-info/RECORD
